vblf/__init__.py
vblf/can.py
vblf/constants.py
vblf/ethernet.py
vblf/flexray.py
vblf/general.py
vblf/lin.py
vblf/most.py
vblf/py.typed
vblf/reader.py
vblf/tp_diag.py
vblf/writer.py
vblf-0.2.1.dist-info/licenses/LICENSE
vblf-0.2.1.dist-info/METADATA
vblf-0.2.1.dist-info/WHEEL
vblf-0.2.1.dist-info/top_level.txt
vblf-0.2.1.dist-info/RECORD
