Metadata-Version: 2.4
Name: vblf
Version: 0.2.1
Summary: A library to read and write Vector BLF files (binary log format)
Author-email: Artur Drogunow <Artur.Drogunow@zf.com>
License: MIT
Project-URL: Issues, https://github.com/zariiii9003/vblf/issues
Project-URL: Source, https://github.com/zariiii9003/vblf
Project-URL: Homepage, https://github.com/zariiii9003/vblf
Keywords: BLF,Vector,binary log format,Automotive
Classifier: Programming Language :: Python :: 3
Classifier: License :: OSI Approved :: MIT License
Classifier: Operating System :: OS Independent
Requires-Python: >=3.9
License-File: LICENSE
Requires-Dist: typing_extensions>=4.0.0
Dynamic: license-file
